shounak_lib/sdk/sb_s3_uploader.py
shounak_lib-1.0.1.dist-info/METADATA
shounak_lib-1.0.1.dist-info/WHEEL
shounak_lib-1.0.1.dist-info/top_level.txt
shounak_lib-1.0.1.dist-info/RECORD
