Metadata-Version: 2.1
Name: shounak-lib
Version: 1.0.1
Summary: Python library to upload profile photo
Home-page: https://github.com/shounak1/shounak_lib
Author: Shounak Bhandekar
Author-email: shounakbhandekar96@gmail.com
License: UNKNOWN
Platform: UNKNOWN
Requires-Dist: colorama
Requires-Dist: colorlog
Requires-Dist: requests
